[
    {
        "proteina_1": "2Y7B",
        "proteina_2": "5EFX",
        "scores": {
            "combined_score": 0.501,
            "tscore": 0,
            "dscore": 0,
            "escore": 0,
            "pscore": 0,
            "nscore": 0
        }
    },
    {
        "proteina_1": "2Y7B",
        "proteina_2": "4L6Q",
        "scores": {
            "combined_score": 0.548,
            "tscore": 0,
            "dscore": 0,
            "escore": 0,
            "pscore": 0,
            "nscore": 0
        }
    },
    {
        "proteina_1": "2Y7B",
        "proteina_2": "1AM4",
        "scores": {
            "combined_score": 0.576,
            "tscore": 0,
            "dscore": 0,
            "escore": 0,
            "pscore": 0,
            "nscore": 0
        }
    },
    {
        "proteina_1": "2Y7B",
        "proteina_2": "2V55",
        "scores": {
            "combined_score": 0.681,
            "tscore": 0,
            "dscore": 0,
            "escore": 0,
            "pscore": 0,
            "nscore": 0
        }
    },
    {
        "proteina_1": "2Y7B",
        "proteina_2": "1S1C",
        "scores": {
            "combined_score": 0.999,
            "tscore": 0,
            "dscore": 0,
            "escore": 0,
            "pscore": 0,
            "nscore": 0
        }
    },
    {
        "proteina_1": "1AM4",
        "proteina_2": "5EFX",
        "scores": {
            "combined_score": 0.412,
            "tscore": 0,
            "dscore": 0,
            "escore": 0,
            "pscore": 0,
            "nscore": 0
        }
    },
    {
        "proteina_1": "1AM4",
        "proteina_2": "4L6Q",
        "scores": {
            "combined_score": 0.524,
            "tscore": 0,
            "dscore": 0,
            "escore": 0,
            "pscore": 0,
            "nscore": 0
        }
    },
    {
        "proteina_1": "1AM4",
        "proteina_2": "2V55",
        "scores": {
            "combined_score": 0.575,
            "tscore": 0,
            "dscore": 0,
            "escore": 0,
            "pscore": 0,
            "nscore": 0
        }
    },
    {
        "proteina_1": "1AM4",
        "proteina_2": "1S1C",
        "scores": {
            "combined_score": 0.999,
            "tscore": 0,
            "dscore": 0,
            "escore": 0,
            "pscore": 0,
            "nscore": 0
        }
    },
    {
        "proteina_1": "4L6Q",
        "proteina_2": "5EFX",
        "scores": {
            "combined_score": 0.426,
            "tscore": 0,
            "dscore": 0,
            "escore": 0,
            "pscore": 0,
            "nscore": 0
        }
    },
    {
        "proteina_1": "4L6Q",
        "proteina_2": "1TXD",
        "scores": {
            "combined_score": 0.667,
            "tscore": 0,
            "dscore": 0,
            "escore": 0,
            "pscore": 0,
            "nscore": 0
        }
    },
    {
        "proteina_1": "4L6Q",
        "proteina_2": "1HTJ",
        "scores": {
            "combined_score": 0.69,
            "tscore": 0,
            "dscore": 0,
            "escore": 0,
            "pscore": 0,
            "nscore": 0
        }
    },
    {
        "proteina_1": "4L6Q",
        "proteina_2": "2V55",
        "scores": {
            "combined_score": 0.988,
            "tscore": 0,
            "dscore": 0,
            "escore": 0,
            "pscore": 0,
            "nscore": 0
        }
    },
    {
        "proteina_1": "4L6Q",
        "proteina_2": "1S1C",
        "scores": {
            "combined_score": 0.998,
            "tscore": 0,
            "dscore": 0,
            "escore": 0,
            "pscore": 0,
            "nscore": 0
        }
    },
    {
        "proteina_1": "2DRN",
        "proteina_2": "1TXD",
        "scores": {
            "combined_score": 0.585,
            "tscore": 0,
            "dscore": 0,
            "escore": 0,
            "pscore": 0,
            "nscore": 0
        }
    },
    {
        "proteina_1": "2DRN",
        "proteina_2": "1HTJ",
        "scores": {
            "combined_score": 0.92,
            "tscore": 0,
            "dscore": 0,
            "escore": 0,
            "pscore": 0,
            "nscore": 0
        }
    },
    {
        "proteina_1": "2DRN",
        "proteina_2": "1S1C",
        "scores": {
            "combined_score": 0.999,
            "tscore": 0,
            "dscore": 0,
            "escore": 0,
            "pscore": 0,
            "nscore": 0
        }
    },
    {
        "proteina_1": "5EFX",
        "proteina_2": "2V55",
        "scores": {
            "combined_score": 0.433,
            "tscore": 0,
            "dscore": 0,
            "escore": 0,
            "pscore": 0,
            "nscore": 0
        }
    },
    {
        "proteina_1": "5EFX",
        "proteina_2": "1S1C",
        "scores": {
            "combined_score": 0.999,
            "tscore": 0,
            "dscore": 0,
            "escore": 0,
            "pscore": 0,
            "nscore": 0
        }
    },
    {
        "proteina_1": "1HTJ",
        "proteina_2": "2V55",
        "scores": {
            "combined_score": 0.707,
            "tscore": 0,
            "dscore": 0,
            "escore": 0,
            "pscore": 0,
            "nscore": 0
        }
    },
    {
        "proteina_1": "1HTJ",
        "proteina_2": "1TXD",
        "scores": {
            "combined_score": 0.965,
            "tscore": 0,
            "dscore": 0,
            "escore": 0,
            "pscore": 0,
            "nscore": 0
        }
    },
    {
        "proteina_1": "1HTJ",
        "proteina_2": "1S1C",
        "scores": {
            "combined_score": 0.999,
            "tscore": 0,
            "dscore": 0,
            "escore": 0,
            "pscore": 0,
            "nscore": 0
        }
    },
    {
        "proteina_1": "1TXD",
        "proteina_2": "2V55",
        "scores": {
            "combined_score": 0.707,
            "tscore": 0,
            "dscore": 0,
            "escore": 0,
            "pscore": 0,
            "nscore": 0
        }
    },
    {
        "proteina_1": "1TXD",
        "proteina_2": "1S1C",
        "scores": {
            "combined_score": 0.999,
            "tscore": 0,
            "dscore": 0,
            "escore": 0,
            "pscore": 0,
            "nscore": 0
        }
    },
    {
        "proteina_1": "2V55",
        "proteina_2": "1S1C",
        "scores": {
            "combined_score": 0.999,
            "tscore": 0,
            "dscore": 0,
            "escore": 0,
            "pscore": 0,
            "nscore": 0
        }
    }
]